{
  "productName": "jacc",
  "version": "0.1.0",
  "identifier": "com.jackit.jacc",
  "build": {
    "beforeDevCommand": "pnpm dev",
    "devUrl": "http://localhost:5173",
    "beforeBuildCommand": "pnpm build",
    "frontendDist": "../dist"
  },
  "app": {
    "windows": [
      {
        "title": "jacc",
        "width": 800,
        "height": 560,
        "resizable": true,
        "decorations": false,
        "center": true,
        "minWidth": 640,
        "minHeight": 400
      }
    ],
    "security": {
      "csp": "default-src 'self'; style-src 'self' 'unsafe-inline'; connect-src 'self' https: http:"
    }
  },
  "plugins": {
    "dialog": {},
    "shell": {
      "open": true
    }
  }
}
